deobfasw/__init__.py
deobfasw/deobfasw.py
deobfaswfastimport-0.0.2.dist-info/METADATA
deobfaswfastimport-0.0.2.dist-info/WHEEL
deobfaswfastimport-0.0.2.dist-info/top_level.txt
deobfaswfastimport-0.0.2.dist-info/RECORD
