Metadata-Version: 2.1
Name: deobfaswfastimport
Version: 0.0.2
Summary: Deobfuscator fast import
Author: AppleSW
Author-email: Sig.Apple.Fruit@gmail.com
Keywords: python,fast,import,deobfuscator
Classifier: Development Status :: 1 - Planning
Classifier: Intended Audience :: Developers
Classifier: Programming Language :: Python :: 3
Classifier: Operating System :: Unix
Classifier: Operating System :: Microsoft :: Windows
